VesicleYOLO_pentadec/__init__.py
VesicleYOLO_pentadec/analyze.py
vesicleyolo_pentadec-0.0.2.dist-info/METADATA
vesicleyolo_pentadec-0.0.2.dist-info/WHEEL
vesicleyolo_pentadec-0.0.2.dist-info/RECORD
