Metadata-Version: 2.4
Name: VesicleYOLO_pentadec
Version: 0.0.2
Summary: A simple package created to easily apply YOLO-based vesicle detection to fluorescence microscopy images.
Project-URL: Homepage, https://github.com/pypa/sampleproject
Project-URL: Issues, https://github.com/pypa/sampleproject/issues
Author-email: Julian Gard <julianlgard@gmail.com>
Classifier: Operating System :: OS Independent
Classifier: Programming Language :: Python :: 3
Requires-Python: >=3.12
